passgen-cli/__init__.py
passgen-cli/passgen_cli.py
passgen_cli-1.4.dist-info/DESCRIPTION.rst
passgen_cli-1.4.dist-info/METADATA
passgen_cli-1.4.dist-info/RECORD
passgen_cli-1.4.dist-info/WHEEL
passgen_cli-1.4.dist-info/entry_points.txt
passgen_cli-1.4.dist-info/metadata.json
passgen_cli-1.4.dist-info/top_level.txt
passgencli/__init__.py
passgencli/passgencli.py
