Metadata-Version: 2.0
Name: passgen-cli
Version: 1.4
Summary: Python command line password generator.
Home-page: https://github.com/Colbyter/passgen-cli
Author: Colby Alladaye
Author-email: colbyter@gmail.com
License: MIT
Keywords: password generator
Platform: UNKNOWN
Classifier: Intended Audience :: Developers
Classifier: License :: OSI Approved :: MIT License
Classifier: Programming Language :: Python
Classifier: Programming Language :: Python :: 3
Classifier: Programming Language :: Python :: 2.7
Classifier: Programming Language :: Python :: 3.5
Classifier: Programming Language :: Python :: 3.6
Classifier: Natural Language :: English
Requires-Dist: click
